pyrheed/__init__.py
pyrheed/__main__.py
pyrheed/bar_chart.py
pyrheed/boundary_statistics.py
pyrheed/broadening.py
pyrheed/browser.py
pyrheed/canvas.py
pyrheed/configuration.py
pyrheed/cursor.py
pyrheed/generate_report.py
pyrheed/gmm.py
pyrheed/graph_3D_surface.py
pyrheed/kikuchi.py
pyrheed/manual_fit.py
pyrheed/my_widgets.py
pyrheed/plot_chart.py
pyrheed/preference.py
pyrheed/process.py
pyrheed/process_monitor.py
pyrheed/profile_chart.py
pyrheed/properties.py
pyrheed/reciprocal_space_mapping.py
pyrheed/regularization.py
pyrheed/scenario.py
pyrheed/scipy_test.py
pyrheed/simulate_RHEED.py
pyrheed/statistical_factor.py
pyrheed/translational_antiphase_domain.py
pyrheed/window.py
pyrheed/write_scenario.py
pyrheed/configuration/__init__.py
pyrheed/configuration/configuration.ini
pyrheed/configuration/default_scenario.ini
pyrheed/data/__init__.py
pyrheed/data/files/AtomicFormFactors.xlsx
pyrheed/data/files/AtomicRadii.xlsx
pyrheed/data/files/__init__.py
pyrheed/data/icons/__init__.py
pyrheed/data/icons/arc.svg
pyrheed/data/icons/arc_dark.svg
pyrheed/data/icons/dark.svg
pyrheed/data/icons/dark_dark.svg
pyrheed/data/icons/fit.svg
pyrheed/data/icons/fit_dark.svg
pyrheed/data/icons/fliplr.svg
pyrheed/data/icons/fliplr_dark.svg
pyrheed/data/icons/flipud.svg
pyrheed/data/icons/flipud_dark.svg
pyrheed/data/icons/icon.png
pyrheed/data/icons/light.svg
pyrheed/data/icons/light_dark.svg
pyrheed/data/icons/line.svg
pyrheed/data/icons/line_dark.svg
pyrheed/data/icons/move.svg
pyrheed/data/icons/move_dark.svg
pyrheed/data/icons/open.svg
pyrheed/data/icons/open_dark.svg
pyrheed/data/icons/rectangle.svg
pyrheed/data/icons/rectangle_dark.svg
pyrheed/data/icons/save as.svg
pyrheed/data/icons/save as_dark.svg
pyrheed/data/icons/zoom in.svg
pyrheed/data/icons/zoom in_dark.svg
pyrheed/data/icons/zoom out.svg
pyrheed/data/icons/zoom out_dark.svg
PyRHEED-1.1.0.dist-info/LICENSE
PyRHEED-1.1.0.dist-info/METADATA
PyRHEED-1.1.0.dist-info/WHEEL
PyRHEED-1.1.0.dist-info/top_level.txt
PyRHEED-1.1.0.dist-info/RECORD
