Metadata-Version: 2.1
Name: PyRHEED
Version: 1.1.0
Summary: A python package for RHEED data analysis and simulation
Author-email: Yu Xiang <yux1991@gmail.com>
Project-URL: Homepage, https://github.com/yux1991/PyRHEED
Project-URL: Issues, https://github.com/yux1991/PyRHEED/issues
Classifier: Programming Language :: Python :: 3
Classifier: License :: OSI Approved :: MIT License
Classifier: Operating System :: OS Independent
Requires-Python: >=3.12
License-File: LICENSE
Requires-Dist: astropy >=6.1.0
Requires-Dist: lxml >=5.2.2
Requires-Dist: matplotlib >=3.9.0
Requires-Dist: numpy >=1.26.4
Requires-Dist: openpyxl >=3.1.2
Requires-Dist: pandas >=2.2.2
Requires-Dist: pillow >=10.3.0
Requires-Dist: plotly >=5.22.0
Requires-Dist: pymatgen >=2024.5.1
Requires-Dist: PyQt6 >=6.7.0
Requires-Dist: PyQt6-Charts >=6.7.0
Requires-Dist: PyQt6-DataVisualization >=6.7.0
Requires-Dist: rawpy >=0.21.0
Requires-Dist: scikit-learn >=1.4.2
Requires-Dist: scipy >=1.13.0
Requires-Dist: shapely >=2.0.4
Requires-Dist: tqdm >=4.66.4
Requires-Dist: urllib3 >=2.2.1
Requires-Dist: xlrd >=2.0.1
